django_federation_auditlog/__init__.py
django_federation_auditlog/admin.py
django_federation_auditlog/apps.py
django_federation_auditlog/diff.py
django_federation_auditlog/middleware.py
django_federation_auditlog/migrations/0001_initial.py
django_federation_auditlog/migrations/__init__.py
django_federation_auditlog/mixins.py
django_federation_auditlog/models.py
django_federation_auditlog/receivers.py
django_federation_auditlog/registry.py
django_federation_auditlog/tests.py
django_federation_auditlog-1.1.0.dist-info/METADATA
django_federation_auditlog-1.1.0.dist-info/WHEEL
django_federation_auditlog-1.1.0.dist-info/RECORD
