Metadata-Version: 2.1
Name: django-federation-auditlog
Version: 1.1.0
Summary: 
Author: Anderson Marques
Author-email: anderson89marques@gmail.com
Requires-Python: >=3.7,<4.0
Classifier: Programming Language :: Python :: 3
Classifier: Programming Language :: Python :: 3.7
Classifier: Programming Language :: Python :: 3.8
Classifier: Programming Language :: Python :: 3.9
Classifier: Programming Language :: Python :: 3.10
Classifier: Programming Language :: Python :: 3.11
Requires-Dist: django-auditlog (==2.0.0)
Requires-Dist: djangorestframework (>=3.11,<4.0)
Requires-Dist: djangorestframework-simplejwt (>=5.2,<6.0)
